minisynth/DatasetManager.py
minisynth/MiniSynth.py
minisynth/MiniSynthFM.py
minisynth/MiniSynthSubtractive.py
minisynth/ModGenerator.py
minisynth/Scale.py
minisynth/WavetableGenerator.py
minisynth/__init__.py
minisynth-0.1.3.dist-info/licenses/LICENSE
minisynth-0.1.3.dist-info/METADATA
minisynth-0.1.3.dist-info/WHEEL
minisynth-0.1.3.dist-info/top_level.txt
minisynth-0.1.3.dist-info/RECORD
